dateparserpython/__init__.py
dateparserpython/dictionary.py
dateparserpython/display.py
dateparserpython/helper.py
dateparserpython/models.py
dateparserpython/parser.py
dateparserpython/prediction.py
dateparserpython/py.typed
rm_date_parser-0.2.2.dist-info/licenses/LICENSE
rm_date_parser-0.2.2.dist-info/METADATA
rm_date_parser-0.2.2.dist-info/WHEEL
rm_date_parser-0.2.2.dist-info/top_level.txt
rm_date_parser-0.2.2.dist-info/RECORD
