Metadata-Version: 2.4
Name: rm-date-parser
Version: 0.2.2
Summary: Finds every date in text and returns each one with the detected format
Author-email: Vaibhav Singh <admin@rationalminds.net>
License-Expression: MIT
Project-URL: Homepage, https://github.com/vbhavsingh/DateParserPython
Project-URL: Issues, https://github.com/vbhavsingh/DateParserPython/issues
Keywords: date,parser,nlp,datetime
Classifier: Development Status :: 3 - Alpha
Classifier: Intended Audience :: Developers
Classifier: Programming Language :: Python
Classifier: Programming Language :: Python :: 3
Classifier: Programming Language :: Python :: 3.9
Classifier: Programming Language :: Python :: 3.10
Classifier: Programming Language :: Python :: 3.11
Classifier: Programming Language :: Python :: 3.12
Classifier: Topic :: Text Processing :: Linguistic
Classifier: Topic :: Software Development :: Libraries :: Python Modules
Requires-Python: >=3.9
License-File: LICENSE
Dynamic: license-file
